open163/__init__.py
open163-0.0.1.dist-info/METADATA
open163-0.0.1.dist-info/WHEEL
open163-0.0.1.dist-info/top_level.txt
open163-0.0.1.dist-info/RECORD
